Workbook

Sheet PANEL
A1: DASHBOARD EJECUTIVO – CONTROL PROPUESTA MOP
A2: ="Última actualización: "&TEXT(TODAY(),"dd-mm-yyyy")&" | Control dinámico con dropdowns por Estado, Prioridad y Responsable" -> Última actualización: 22-05-yyyy | Control dinámico con dropdowns por Estado, Prioridad y Responsable
A4: TOTAL ÍTEMS | C4: % AVANCE | E4: PENDIENTES | G4: NO CUMPLE | I4: CRÍTICOS EN RIESGO | K4: DECISIÓN EJECUTIVA
A5: =SUM(C10:C16) -> 155 | C5: =IFERROR((SUM(D10:D16)+SUM(G10:G16))/SUM(C10:C16),0) -> 0.20645161 | E5: =SUM(E10:E16) -> 119 | G5: =SUM(F10:F16) -> 4 | I5: =SUM(I10:I16) -> 61 | K5: =IF(I5>0,"NO GO / ACCIÓN",IF(G5>0,"ALERTA",IF(C5>=0.95,"GO","EN CURSO"))) -> NO GO / ACCIÓN
A8: RESUMEN EJECUTIVO POR MÓDULO
A9: MÓDULO | B9: HOJA | C9: ÍTEMS | D9: ✓ CUMPLE | E9: ⚠ PEND. | F9: ✗ NO CUMPLE | G9: N/A | H9: % AVANCE | I9: CRÍT. RIESGO | J9: ENFOQUE | K9: ACCIÓN SUGERIDA
A10: 1. Revisión de Bases | B10: BASES | C10: =COUNT(BASES!$B$7:$B$39) -> 27 | D10: =COUNTIF(BASES!$F$7:$F$39,"✓ CUMPLE") -> 0 | E10: =COUNTIF(BASES!$F$7:$F$39,"⚠ PENDIENTE") -> 27 | F10: =COUNTIF(BASES!$F$7:$F$39,"✗ NO CUMPLE") -> 0 | G10: =COUNTIF(BASES!$F$7:$F$39,"N/A") -> 0 | H10: =IFERROR((D10+G10)/C10,0) -> 0 | I10: =COUNTIFS(BASES!$E$7:$E$39,"CRÍTICO",BASES!$F$7:$F$39,"⚠ PENDIENTE")+COUNTIFS(BASES!$E$7:$E$39,"CRÍTICO",BASES!$F$7:$F$39,"✗ NO CUMPLE") -> 19 | J10: =IF(I10>0,"Resolver críticos",IF(F10>0,"Corregir no cumple",IF(E10>0,"Cerrar pendientes","Control OK"))) -> Resolver críticos | K10: =IF(I10>0,"Escalar a Jefe Propuesta",IF(F10>0,"Corregir evidencia / documento",IF(E10>0,"Asignar fecha de cierre","Mantener monitoreo"))) -> Escalar a Jefe Propuesta
A11: 2. Equipo / CV | B11: PERSONAL | C11: =COUNT(PERSONAL!$B$7:$B$39) -> 27 | D11: =COUNTIF(PERSONAL!$F$7:$F$39,"✓ CUMPLE") -> 0 | E11: =COUNTIF(PERSONAL!$F$7:$F$39,"⚠ PENDIENTE") -> 27 | F11: =COUNTIF(PERSONAL!$F$7:$F$39,"✗ NO CUMPLE") -> 0 | G11: =COUNTIF(PERSONAL!$F$7:$F$39,"N/A") -> 0 | H11: =IFERROR((D11+G11)/C11,0) -> 0 | I11: =COUNTIFS(PERSONAL!$E$7:$E$39,"CRÍTICO",PERSONAL!$F$7:$F$39,"⚠ PENDIENTE")+COUNTIFS(PERSONAL!$E$7:$E$39,"CRÍTICO",PERSONAL!$F$7:$F$39,"✗ NO CUMPLE") -> 14 | J11: =IF(I11>0,"Resolver críticos",IF(F11>0,"Corregir no cumple",IF(E11>0,"Cerrar pendientes","Control OK"))) -> Resolver críticos | K11: =IF(I11>0,"Escalar a Jefe Propuesta",IF(F11>0,"Corregir evidencia / documento",IF(E11>0,"Asignar fecha de cierre","Mantener monitoreo"))) -> Escalar a Jefe Propuesta
A12: 3. Metodología | B12: METODOLOGIA | C12: =COUNT(METODOLOGIA!$B$7:$B$39) -> 20 | D12: =COUNTIF(METODOLOGIA!$F$7:$F$39,"✓ CUMPLE") -> 9 | E12: =COUNTIF(METODOLOGIA!$F$7:$F$39,"⚠ PENDIENTE") -> 10 | F12: =COUNTIF(METODOLOGIA!$F$7:$F$39,"✗ NO CUMPLE") -> 1 | G12: =COUNTIF(METODOLOGIA!$F$7:$F$39,"N/A") -> 0 | H12: =IFERROR((D12+G12)/C12,0) -> 0.45 | I12: =COUNTIFS(METODOLOGIA!$E$7:$E$39,"CRÍTICO",METODOLOGIA!$F$7:$F$39,"⚠ PENDIENTE")+COUNTIFS(METODOLOGIA!$E$7:$E$39,"CRÍTICO",METODOLOGIA!$F$7:$F$39,"✗ NO CUMPLE") -> 1 | J12: =IF(I12>0,"Resolver críticos",IF(F12>0,"Corregir no cumple",IF(E12>0,"Cerrar pendientes","Control OK"))) -> Resolver críticos | K12: =IF(I12>0,"Escalar a Jefe Propuesta",IF(F12>0,"Corregir evidencia / documento",IF(E12>0,"Asignar fecha de cierre","Mantener monitoreo"))) -> Escalar a Jefe Propuesta
A13: 4. Oferta Económica | B13: ECONOMICA | C13: =COUNT(ECONOMICA!$B$7:$B$39) -> 20 | D13: =COUNTIF(ECONOMICA!$F$7:$F$39,"✓ CUMPLE") -> 15 | E13: =COUNTIF(ECONOMICA!$F$7:$F$39,"⚠ PENDIENTE") -> 2 | F13: =COUNTIF(ECONOMICA!$F$7:$F$39,"✗ NO CUMPLE") -> 3 | G13: =COUNTIF(ECONOMICA!$F$7:$F$39,"N/A") -> 0 | H13: =IFERROR((D13+G13)/C13,0) -> 0.75 | I13: =COUNTIFS(ECONOMICA!$E$7:$E$39,"CRÍTICO",ECONOMICA!$F$7:$F$39,"⚠ PENDIENTE")+COUNTIFS(ECONOMICA!$E$7:$E$39,"CRÍTICO",ECONOMICA!$F$7:$F$39,"✗ NO CUMPLE") -> 2 | J13: =IF(I13>0,"Resolver críticos",IF(F13>0,"Corregir no cumple",IF(E13>0,"Cerrar pendientes","Control OK"))) -> Resolver críticos | K13: =IF(I13>0,"Escalar a Jefe Propuesta",IF(F13>0,"Corregir evidencia / documento",IF(E13>0,"Asignar fecha de cierre","Mantener monitoreo"))) -> Escalar a Jefe Propuesta
A14: 5. Control Documental | B14: DOCUMENTAL | C14: =COUNT(DOCUMENTAL!$B$7:$B$39) -> 23 | D14: =COUNTIF(DOCUMENTAL!$F$7:$F$39,"✓ CUMPLE") -> 8 | E14: =COUNTIF(DOCUMENTAL!$F$7:$F$39,"⚠ PENDIENTE") -> 15 | F14: =COUNTIF(DOCUMENTAL!$F$7:$F$39,"✗ NO CUMPLE") -> 0 | G14: =COUNTIF(DOCUMENTAL!$F$7:$F$39,"N/A") -> 0 | H14: =IFERROR((D14+G14)/C14,0) -> 0.34782609 | I14: =COUNTIFS(DOCUMENTAL!$E$7:$E$39,"CRÍTICO",DOCUMENTAL!$F$7:$F$39,"⚠ PENDIENTE")+COUNTIFS(DOCUMENTAL!$E$7:$E$39,"CRÍTICO",DOCUMENTAL!$F$7:$F$39,"✗ NO CUMPLE") -> 6 | J14: =IF(I14>0,"Resolver críticos",IF(F14>0,"Corregir no cumple",IF(E14>0,"Cerrar pendientes","Control OK"))) -> Resolver críticos | K14: =IF(I14>0,"Escalar a Jefe Propuesta",IF(F14>0,"Corregir evidencia / documento",IF(E14>0,"Asignar fecha de cierre","Mantener monitoreo"))) -> Escalar a Jefe Propuesta
A15: 6. Gestión de Calidad | B15: CALIDAD | C15: =COUNT(CALIDAD!$B$7:$B$39) -> 16 | D15: =COUNTIF(CALIDAD!$F$7:$F$39,"✓ CUMPLE") -> 0 | E15: =COUNTIF(CALIDAD!$F$7:$F$39,"⚠ PENDIENTE") -> 16 | F15: =COUNTIF(CALIDAD!$F$7:$F$39,"✗ NO CUMPLE") -> 0 | G15: =COUNTIF(CALIDAD!$F$7:$F$39,"N/A") -> 0 | H15: =IFERROR((D15+G15)/C15,0) -> 0 | I15: =COUNTIFS(CALIDAD!$E$7:$E$39,"CRÍTICO",CALIDAD!$F$7:$F$39,"⚠ PENDIENTE")+COUNTIFS(CALIDAD!$E$7:$E$39,"CRÍTICO",CALIDAD!$F$7:$F$39,"✗ NO CUMPLE") -> 6 | J15: =IF(I15>0,"Resolver críticos",IF(F15>0,"Corregir no cumple",IF(E15>0,"Cerrar pendientes","Control OK"))) -> Resolver críticos | K15: =IF(I15>0,"Escalar a Jefe Propuesta",IF(F15>0,"Corregir evidencia / documento",IF(E15>0,"Asignar fecha de cierre","Mantener monitoreo"))) -> Escalar a Jefe Propuesta
A16: 7. Cierre y Entrega | B16: CIERRE | C16: =COUNT(CIERRE!$B$7:$B$39) -> 22 | D16: =COUNTIF(CIERRE!$F$7:$F$39,"✓ CUMPLE") -> 0 | E16: =COUNTIF(CIERRE!$F$7:$F$39,"⚠ PENDIENTE") -> 22 | F16: =COUNTIF(CIERRE!$F$7:$F$39,"✗ NO CUMPLE") -> 0 | G16: =COUNTIF(CIERRE!$F$7:$F$39,"N/A") -> 0 | H16: =IFERROR((D16+G16)/C16,0) -> 0 | I16: =COUNTIFS(CIERRE!$E$7:$E$39,"CRÍTICO",CIERRE!$F$7:$F$39,"⚠ PENDIENTE")+COUNTIFS(CIERRE!$E$7:$E$39,"CRÍTICO",CIERRE!$F$7:$F$39,"✗ NO CUMPLE") -> 13 | J16: =IF(I16>0,"Resolver críticos",IF(F16>0,"Corregir no cumple",IF(E16>0,"Cerrar pendientes","Control OK"))) -> Resolver críticos | K16: =IF(I16>0,"Escalar a Jefe Propuesta",IF(F16>0,"Corregir evidencia / documento",IF(E16>0,"Asignar fecha de cierre","Mantener monitoreo"))) -> Escalar a Jefe Propuesta
A17: TOTAL GENERAL | C17: =SUM(C10:C16) -> 155 | D17: =SUM(D10:D16) -> 32 | E17: =SUM(E10:E16) -> 119 | F17: =SUM(F10:F16) -> 4 | G17: =SUM(G10:G16) -> 0 | H17: =IFERROR((D17+G17)/C17,0) -> 0.20645161 | I17: =SUM(I10:I16) -> 61 | J17: =IF(I17>0,"RIESGO CRÍTICO",IF(F17>0,"ALERTA","BAJO CONTROL")) -> RIESGO CRÍTICO | K17: =IF(I17>0,"Reunión de cierre + plan correctivo",IF(E17>0,"Priorizar pendientes","Lista para revisión final")) -> Reunión de cierre + plan correctivo
A19: DISTRIBUCIÓN GLOBAL DE ESTADOS | D19: CRÍTICOS EN RIESGO POR MÓDULO | L19: Módulo | M19: Críticos
A20: Estado | B20: Cantidad | C20: % | D20: Módulo | G20: Críticos | L20: =A10 -> 1. Revisión de Bases | M20: =I10 -> 19
A21: ✓ CUMPLE | B21: =D17 -> 32 | C21: =IFERROR(B21/$C$17,0) -> 0.20645161 | D21: =A10 -> 1. Revisión de Bases | G21: =I10 -> 19 | L21: =A11 -> 2. Equipo / CV | M21: =I11 -> 14
A22: ⚠ PENDIENTE | B22: =E17 -> 119 | C22: =IFERROR(B22/$C$17,0) -> 0.76774194 | D22: =A11 -> 2. Equipo / CV | G22: =I11 -> 14 | L22: =A12 -> 3. Metodología | M22: =I12 -> 1
A23: ✗ NO CUMPLE | B23: =F17 -> 4 | C23: =IFERROR(B23/$C$17,0) -> 0.025806452 | D23: =A12 -> 3. Metodología | G23: =I12 -> 1 | L23: =A13 -> 4. Oferta Económica | M23: =I13 -> 2
A24: N/A | B24: =G17 -> 0 | C24: =IFERROR(B24/$C$17,0) -> 0 | D24: =A13 -> 4. Oferta Económica | G24: =I13 -> 2 | L24: =A14 -> 5. Control Documental | M24: =I14 -> 6
D25: =A14 -> 5. Control Documental | G25: =I14 -> 6 | L25: =A15 -> 6. Gestión de Calidad | M25: =I15 -> 6
D26: =A15 -> 6. Gestión de Calidad | G26: =I15 -> 6 | L26: =A16 -> 7. Cierre y Entrega | M26: =I16 -> 13
D27: =A16 -> 7. Cierre y Entrega | G27: =I16 -> 13
A29: LECTURA EJECUTIVA / PRÓXIMAS ACCIONES
A30: 1 | B30: Si existen críticos en riesgo, la propuesta no debe pasar a cierre sin evidencia correctiva.
A31: 2 | B31: Priorice módulos con mayor número de pendientes y no conformidades.
A32: 3 | B32: Use Observación / Evidencia para dejar trazabilidad del documento revisado.
A33: 4 | B33: Revisar el dashboard después de cada cambio de Estado.
A34: 5 | B34: Antes de entregar, buscar que % avance sea ≥ 95% y críticos en riesgo = 0.

Sheet BASES
B2: BASES
H3: =COUNTIF(F6:F500,"✓ CUMPLE") -> 0
B4: Completa el Estado con el dropdown. Agrega observaciones y evidencias en columna G.
B5: # | C5: ÍTEM / REQUISITO A VERIFICAR | D5: RESPONSABLE | E5: PRIORIDAD | F5: ESTADO | G5: OBSERVACIÓN / EVIDENCIA | H5: REF. BASES
B6: ▶ A. LECTURA INICIAL Y ACLARACIONES
B7: 1 | C7: Leer bases completas: administrativas, técnicas y especiales | D7: Jefe Propuesta | E7: CRÍTICO | F7: ⚠ PENDIENTE | H7: Req. básico
B8: 2 | C8: Leer todos los anexos y formularios exigidos | D8: Analista 1 | E8: CRÍTICO | F8: ⚠ PENDIENTE | H8: Req. básico
B9: 3 | C9: Registrar fecha límite de consultas / aclaraciones | D9: Analista 1 | E9: CRÍTICO | F9: ⚠ PENDIENTE | H9: Plazo crítico
B10: 4 | C10: Registrar fecha y lugar de apertura técnica y económica | D10: Analista 2 | E10: CRÍTICO | F10: ⚠ PENDIENTE | H10: Plazo crítico
B11: 5 | C11: Leer todas las aclaraciones publicadas en el portal | D11: Jefe Propuesta | E11: CRÍTICO | F11: ⚠ PENDIENTE | H11: Modifica bases
B12: 6 | C12: Confirmar asistencia a visita a terreno (si es obligatoria) | D12: Analista 1 | E12: CRÍTICO | F12: ⚠ PENDIENTE | H12: Req. básico
B13: 7 | C13: Identificar si hay planos, EETT o documentos de referencia adicionales | D13: Analista 2 | E13: ALTO | F13: ⚠ PENDIENTE | H13: Req. técnico
B15: ▶ B. REQUISITOS DE ADMISIBILIDAD
B16: 8 | C16: Verificar monto mínimo de facturación / experiencia previa exigidos | D16: Jefe Propuesta | E16: CRÍTICO | F16: ⚠ PENDIENTE | H16: Fuera de bases
B17: 9 | C17: Verificar inscripción vigente en Chileproveedores (sin observaciones) | D17: Analista 1 | E17: CRÍTICO | F17: ⚠ PENDIENTE | H17: Fuera de bases
B18: 10 | C18: Comprobar si se exige garantía de seriedad: monto, plazo, tipo | D18: Analista 1 | E18: CRÍTICO | F18: ⚠ PENDIENTE | H18: Fuera de bases
B19: 11 | C19: Verificar certificado de deuda tributaria / previsional al día | D19: Analista 2 | E19: CRÍTICO | F19: ⚠ PENDIENTE | H19: Req. básico
B20: 12 | C20: Revisar causales de fuera de bases expresamente listadas en bases | D20: Jefe Propuesta | E20: CRÍTICO | F20: ⚠ PENDIENTE | H20: Fuera de bases
B21: 13 | C21: Identificar declaraciones juradas específicas exigidas | D21: Analista 2 | E21: ALTO | F21: ⚠ PENDIENTE | H21: Admisibilidad
B22: 14 | C22: Confirmar que la empresa puede postular (no está sancionada, inhabilitada) | D22: Jefe Propuesta | E22: CRÍTICO | F22: ⚠ PENDIENTE | H22: Admisibilidad
B24: ▶ C. CRITERIOS DE EVALUACIÓN Y PUNTAJE
B25: 15 | C25: Extraer tabla de criterios con ponderación exacta (% por categoría) | D25: Jefe Propuesta | E25: CRÍTICO | F25: ⚠ PENDIENTE | H25: Puntaje
B26: 16 | C26: Calcular puntaje máximo posible por categoría (metodología, personal, precio) | D26: Jefe Propuesta | E26: CRÍTICO | F26: ⚠ PENDIENTE | H26: Estrategia
B27: 17 | C27: Identificar en qué criterios se puede maximizar puntaje diferenciador | D27: Jefe Propuesta | E27: CRÍTICO | F27: ⚠ PENDIENTE | H27: Estrategia
B28: 18 | C28: Transcribir fórmula exacta de puntaje precio y calcular precio óptimo | D28: Jefe Propuesta | E28: CRÍTICO | F28: ⚠ PENDIENTE | H28: Puntaje precio
B29: 19 | C29: Revisar si metodología tiene sub-criterios evaluados separadamente | D29: Analista 1 | E29: ALTO | F29: ⚠ PENDIENTE | H29: Puntaje
B30: 20 | C30: Revisar si experiencia del equipo tiene sub-puntajes por perfil | D30: Analista 1 | E30: ALTO | F30: ⚠ PENDIENTE | H30: Puntaje
B31: 21 | C31: Identificar si hay bonificaciones o puntos adicionales por compromisos | D31: Analista 2 | E31: MEDIO | F31: ⚠ PENDIENTE | H31: Puntaje
B33: ▶ D. ALCANCE TÉCNICO DEL CONTRATO
B34: 22 | C34: Identificar tipo de contrato (ITO, asesoría, ejecución, conservación vial) | D34: Jefe Propuesta | E34: CRÍTICO | F34: ⚠ PENDIENTE | H34: Alcance
B35: 23 | C35: Definir claramente el alcance de responsabilidades de la asesoría | D35: Jefe Propuesta | E35: CRÍTICO | F35: ⚠ PENDIENTE | H35: Alcance
B36: 24 | C36: Verificar plazo contractual, plazos parciales e hitos de entrega | D36: Analista 1 | E36: CRÍTICO | F36: ⚠ PENDIENTE | H36: Plazo
B37: 25 | C37: Identificar normas específicas aplicables (AASHTO, INN, MOP, ISO, DS 132) | D37: Analista 2 | E37: ALTO | F37: ⚠ PENDIENTE | H37: Normativa
B38: 26 | C38: Revisar si hay presupuesto referencial publicado y su desglose | D38: Jefe Propuesta | E38: ALTO | F38: ⚠ PENDIENTE | H38: Estrategia económica
B39: 27 | C39: Identificar partidas o actividades de alcance ambiguo → enviar aclaración | D39: Analista 1 | E39: ALTO | F39: ⚠ PENDIENTE | H39: Riesgo técnico

Sheet PERSONAL
A1: 3
B2: PERSONAL
H3: =COUNTIF(F6:F500,"✓ CUMPLE") -> 0
B4: Completa el Estado con el dropdown. Agrega observaciones y evidencias en columna G.
B5: # | C5: ÍTEM / REQUISITO A VERIFICAR | D5: RESPONSABLE | E5: PRIORIDAD | F5: ESTADO | G5: OBSERVACIÓN / EVIDENCIA | H5: REF. BASES
B6: ▶ A. JEFE DE ASESORÍA / JEFE DE PROYECTO
B7: 1 | C7: Verificar título profesional exigido (ej: Ing. Civil, Constructor Civil) | D7: Jefe Propuesta | E7: CRÍTICO | F7: ⚠ PENDIENTE | H7: Fuera de bases
B8: 2 | C8: Verificar años de experiencia total y experiencia específica exigidos | D8: Analista 1 | E8: CRÍTICO | F8: ⚠ PENDIENTE | H8: Fuera de bases
B9: 3 | C9: Confirmar que la experiencia acreditada es en proyectos del mismo tipo | D9: Analista 1 | E9: CRÍTICO | F9: ⚠ PENDIENTE | H9: Puntaje
B10: 4 | C10: Revisar que contratos del CV coincidan en nombre, mandante y año | D10: Analista 2 | E10: ALTO | F10: ⚠ PENDIENTE | H10: Consistencia
B11: 5 | C11: Verificar que carta compromiso está firmada, con RUT y fecha vigente | D11: Analista 1 | E11: CRÍTICO | F11: ⚠ PENDIENTE | H11: Fuera de bases
B12: 6 | C12: Comprobar que no está comprometido en otro contrato MOP activo incompatible | D12: Jefe Propuesta | E12: CRÍTICO | F12: ⚠ PENDIENTE | H12: Req. básico
B13: 7 | C13: Calcular puntaje esperado para este perfil según tabla de bases | D13: Jefe Propuesta | E13: CRÍTICO | F13: ⚠ PENDIENTE | H13: Puntaje
B14: 8 | C14: Revisar si la experiencia declarada supera el mínimo para obtener puntaje extra | D14: Analista 1 | E14: ALTO | F14: ⚠ PENDIENTE | H14: Maximizar puntaje
B16: ▶ B. PROFESIONALES COMPLEMENTARIOS OBLIGATORIOS
B17: 9 | C17: Jefe de Topografía: título, experiencia y carta compromiso | D17: Analista 1 | E17: CRÍTICO | F17: ⚠ PENDIENTE | H17: Fuera de bases
B18: 10 | C18: Profesional Residente: título, experiencia y carta compromiso | D18: Analista 1 | E18: CRÍTICO | F18: ⚠ PENDIENTE | H18: Fuera de bases
B19: 11 | C19: Jefe de Laboratorio: título, certificaciones y experiencia | D19: Analista 1 | E19: CRÍTICO | F19: ⚠ PENDIENTE | H19: Fuera de bases
B20: 12 | C20: Prevencionista: título, exp. en obras viales y disponibilidad horaria | D20: Analista 2 | E20: CRÍTICO | F20: ⚠ PENDIENTE | H20: Fuera de bases
B21: 13 | C21: Encargado de Calidad: título y experiencia en sistemas de calidad | D21: Analista 2 | E21: ALTO | F21: ⚠ PENDIENTE | H21: Puntaje
B22: 14 | C22: Encargado Ambiental: título y experiencia en proyectos viales | D22: Analista 2 | E22: ALTO | F22: ⚠ PENDIENTE | H22: Puntaje
B23: 15 | C23: Revisar que profesionales opcionales incluidos también tienen carta compromiso | D23: Analista 1 | E23: ALTO | F23: ⚠ PENDIENTE | H23: Consistencia
B25: ▶ C. REVISIÓN CRUZADA DE CV
B26: 16 | C26: Comparar años de experiencia declarados vs fechas de contratos del CV | D26: Analista 2 | E26: CRÍTICO | F26: ⚠ PENDIENTE | H26: Consistencia
B27: 17 | C27: Verificar que no hay solapamiento imposible de contratos simultáneos | D27: Analista 2 | E27: ALTO | F27: ⚠ PENDIENTE | H27: Riesgo
B28: 18 | C28: Confirmar que los contratos declarados como ITO/Asesoría no sean de ejecución | D28: Analista 1 | E28: ALTO | F28: ⚠ PENDIENTE | H28: Riesgo
B29: 19 | C29: Revisar que proyectos del CV son del mismo tipo al contratado (vial, etc.) | D29: Analista 1 | E29: ALTO | F29: ⚠ PENDIENTE | H29: Puntaje
B30: 20 | C30: Verificar que montos o km de proyectos cumplen umbrales mínimos si aplica | D30: Analista 1 | E30: ALTO | F30: ⚠ PENDIENTE | H30: Puntaje
B31: 21 | C31: Asegurarse que el CV tiene firma del profesional si las bases lo exigen | D31: Analista 2 | E31: MEDIO | F31: ⚠ PENDIENTE | H31: Formal
B32: 22 | C32: Conclusión por cada CV: Cumple / Cumple con riesgo / No cumple | D32: Analista 2 | E32: CRÍTICO | F32: ⚠ PENDIENTE | H32: Control
B34: ▶ D. CONTROL DE CARTAS COMPROMISO
B35: 23 | C35: Carta firmada, con nombre completo, RUT y fecha | D35: Analista 1 | E35: CRÍTICO | F35: ⚠ PENDIENTE | H35: Fuera de bases
B36: 24 | C36: Vigencia de la carta dentro del plazo exigido por bases | D36: Analista 1 | E36: CRÍTICO | F36: ⚠ PENDIENTE | H36: Fuera de bases
B37: 25 | C37: La carta nombra expresamente el contrato/licitación correcto | D37: Analista 2 | E37: ALTO | F37: ⚠ PENDIENTE | H37: Consistencia
B38: 26 | C38: Dedicación horaria declarada coincide con lo exigido | D38: Analista 2 | E38: ALTO | F38: ⚠ PENDIENTE | H38: Req. bases
B39: 27 | C39: No hay incompatibilidad con compromisos en otros contratos vigentes | D39: Jefe Propuesta | E39: ALTO | F39: ⚠ PENDIENTE | H39: Riesgo ético

Sheet METODOLOGIA
B2: METODOLOGIA
H3: =COUNTIF(F6:F500,"✓ CUMPLE") -> 9
B4: Completa el Estado con el dropdown. Agrega observaciones y evidencias en columna G.
B5: # | C5: ÍTEM / REQUISITO A VERIFICAR | D5: RESPONSABLE | E5: PRIORIDAD | F5: ESTADO | G5: OBSERVACIÓN / EVIDENCIA | H5: REF. BASES
B6: ▶ A. ESTRUCTURA Y COHERENCIA
B7: 1 | C7: La metodología está estructurada según los ítems evaluados en bases | D7: Jefe Propuesta | E7: CRÍTICO | F7: ✓ CUMPLE | H7: Puntaje
B8: 2 | C8: Cada sección responde a un criterio específico de las bases (no genérica) | D8: Jefe Propuesta | E8: CRÍTICO | F8: ✓ CUMPLE | H8: Puntaje
B9: 3 | C9: No hay texto reciclado de otras propuestas sin adaptación al contrato | D9: Analista 1 | E9: CRÍTICO | F9: ⚠ PENDIENTE | H9: Riesgo descuento
B10: 4 | C10: Se menciona el nombre del contrato, mandante y zona geográfica correcta | D10: Analista 2 | E10: ALTO | F10: ✓ CUMPLE | H10: Consistencia
B11: 5 | C11: La extensión cumple los límites de páginas si las bases lo establecen | D11: Analista 1 | E11: ALTO | F11: ✗ NO CUMPLE | H11: Req. bases
B12: 6 | C12: El índice de la metodología coincide con el contenido real | D12: Analista 2 | E12: ALTO | F12: ⚠ PENDIENTE | H12: Consistencia
B14: ▶ B. CONTENIDO TÉCNICO EXIGIDO
B15: 7 | C15: Se describe el enfoque y estrategia de trabajo del equipo ITO/asesoría | D15: Jefe Propuesta | E15: CRÍTICO | F15: ✓ CUMPLE | H15: Puntaje
B16: 8 | C16: Se incluye organigrama del equipo con líneas de dependencia y cargos | D16: Analista 1 | E16: ALTO | F16: ✓ CUMPLE | H16: Puntaje
B17: 9 | C17: Se detalla sistema de control de calidad de obras propuesto | D17: Jefe Propuesta | E17: ALTO | F17: ⚠ PENDIENTE | H17: Puntaje calidad
B18: 10 | C18: Se describe sistema de reportes, informes y trazabilidad documental | D18: Analista 1 | E18: ALTO | F18: ⚠ PENDIENTE | H18: Puntaje
B19: 11 | C19: Se incluye plan de comunicaciones con la IF / mandante | D19: Analista 2 | E19: ALTO | F19: ⚠ PENDIENTE | H19: Puntaje
B20: 12 | C20: Se describe gestión de riesgos del contrato | D20: Analista 2 | E20: MEDIO | F20: ✓ CUMPLE | H20: Puntaje
B21: 13 | C21: Se incluye plan de seguridad y prevención (si es exigido) | D21: Analista 2 | E21: ALTO | F21: ✓ CUMPLE | H21: Req. bases
B22: 14 | C22: Se referencia normativa vigente aplicable (MOP, DS 132, ISO, etc.) | D22: Analista 1 | E22: ALTO | F22: ✓ CUMPLE | H22: Puntaje técnico
B23: 15 | C23: Se describe protocolo de control de documentos en terreno | D23: Analista 2 | E23: MEDIO | F23: ✓ CUMPLE | H23: Puntaje calidad
B25: ▶ C. DIFERENCIACIÓN Y VALOR AGREGADO
B26: 16 | C26: Se propone al menos un elemento diferenciador no solicitado pero valorizable | D26: Jefe Propuesta | E26: MEDIO | F26: ⚠ PENDIENTE | H26: Ventaja
B27: 17 | C27: Se describe experiencia previa del equipo en contratos similares | D27: Jefe Propuesta | E27: ALTO | F27: ⚠ PENDIENTE | H27: Puntaje
B28: 18 | C28: Se usa lenguaje alineado con el glosario y terminología de las bases | D28: Analista 1 | E28: ALTO | F28: ⚠ PENDIENTE | H28: Coherencia
B29: 19 | C29: No se usan normas no aplicables al tipo de contrato (ej: ejecución en ITO) | D29: Analista 1 | E29: ALTO | F29: ⚠ PENDIENTE | H29: Riesgo descuento
B30: 20 | C30: Se incluye descripción de herramientas de gestión (software, BIM, GPS, etc.) si aplica | D30: Analista 2 | E30: MEDIO | F30: ⚠ PENDIENTE | H30: Valor agregado

Sheet ECONOMICA
B2: ECONOMICA
H3: =COUNTIF(F6:F500,"✓ CUMPLE") -> 15
B4: Completa el Estado con el dropdown. Agrega observaciones y evidencias en columna G.
B5: # | C5: ÍTEM / REQUISITO A VERIFICAR | D5: RESPONSABLE | E5: PRIORIDAD | F5: ESTADO | G5: OBSERVACIÓN / EVIDENCIA | H5: REF. BASES
B6: ▶ A. ARITMÉTICA Y CONSISTENCIA
B7: 1 | C7: La suma de partidas coincide exactamente con el total ofertado | D7: Jefe Propuesta | E7: CRÍTICO | F7: ✓ CUMPLE | H7: Fuera de bases
B8: 2 | C8: El IVA está correctamente calculado (19% sobre monto neto) | D8: Analista 1 | E8: CRÍTICO | F8: ✓ CUMPLE | H8: Error grave
B9: 3 | C9: Los % de GG y utilidades cuadran con los montos declarados | D9: Analista 1 | E9: CRÍTICO | F9: ✓ CUMPLE | H9: Error grave
B10: 4 | C10: Costo directo + GG + utilidades + IVA = total oferta | D10: Analista 1 | E10: CRÍTICO | F10: ✓ CUMPLE | H10: Consistencia
B11: 5 | C11: No hay errores de transcripción (números al revés, ceros extra) | D11: Analista 2 | E11: CRÍTICO | F11: ✓ CUMPLE | H11: Error grave
B12: 6 | C12: Las fechas en los documentos son anteriores al cierre de la licitación | D12: Analista 2 | E12: CRÍTICO | F12: ✗ NO CUMPLE | H12: Inconsistencia grave
B14: ▶ B. CUMPLIMIENTO DE BASES ECONÓMICAS
B15: 7 | C15: El monto no supera el presupuesto referencial publicado | D15: Jefe Propuesta | E15: CRÍTICO | F15: ✓ CUMPLE | H15: Fuera de bases
B16: 8 | C16: Todos los formularios económicos exigidos están completados y firmados | D16: Analista 1 | E16: CRÍTICO | F16: ✓ CUMPLE | H16: Fuera de bases
B17: 9 | C17: Los precios por profesional son consistentes con el total del contrato | D17: Analista 1 | E17: ALTO | F17: ✓ CUMPLE | H17: Consistencia
B18: 10 | C18: Los valores unitarios son razonables (no subevaluados ni sobre-inflados) | D18: Jefe Propuesta | E18: ALTO | F18: ✗ NO CUMPLE | H18: Estrategia
B19: 11 | C19: Se verificó que los honorarios son consistentes con el mercado | D19: Analista 2 | E19: ALTO | F19: ⚠ PENDIENTE | H19: Credibilidad
B21: ▶ C. ESTRATEGIA DE PRECIO
B22: 12 | C22: Se calculó el precio para obtener puntaje máximo según fórmula de bases | D22: Jefe Propuesta | E22: CRÍTICO | F22: ✓ CUMPLE | H22: Estrategia
B23: 13 | C23: Se simularon escenarios de precio frente a competencia estimada | D23: Jefe Propuesta | E23: ALTO | F23: ✓ CUMPLE | H23: Estrategia
B24: 14 | C24: Se verificó que el precio cubre costos reales (no sub-cotizar con pérdida) | D24: Jefe Propuesta | E24: CRÍTICO | F24: ✓ CUMPLE | H24: Sostenibilidad
B25: 15 | C25: Se documentó la decisión de precio y su fundamento estratégico | D25: Jefe Propuesta | E25: MEDIO | F25: ⚠ PENDIENTE | H25: Trazabilidad
B27: ▶ D. GARANTÍA DE SERIEDAD DE OFERTA
B28: 16 | C28: Monto de la garantía es exactamente el exigido en bases | D28: Analista 1 | E28: CRÍTICO | F28: ✓ CUMPLE | H28: Fuera de bases
B29: 17 | C29: Plazo de vigencia cubre lo exigido + margen de seguridad | D29: Analista 1 | E29: CRÍTICO | F29: ✓ CUMPLE | H29: Fuera de bases
B30: 18 | C30: El beneficiario es el MOP / Dirección correcta (no otra entidad) | D30: Analista 2 | E30: CRÍTICO | F30: ✓ CUMPLE | H30: Fuera de bases
B31: 19 | C31: Tipo de instrumento es el aceptado en bases (boleta, póliza, vale vista) | D31: Analista 2 | E31: CRÍTICO | F31: ✓ CUMPLE | H31: Fuera de bases
B32: 20 | C32: El documento tiene firma y sello del banco o aseguradora | D32: Analista 1 | E32: CRÍTICO | F32: ✗ NO CUMPLE | H32: Validez

Sheet DOCUMENTAL
B2: DOCUMENTAL
H3: =COUNTIF(F6:F500,"✓ CUMPLE") -> 8
B4: Completa el Estado con el dropdown. Agrega observaciones y evidencias en columna G.
B5: # | C5: ÍTEM / REQUISITO A VERIFICAR | D5: RESPONSABLE | E5: PRIORIDAD | F5: ESTADO | G5: OBSERVACIÓN / EVIDENCIA | H5: REF. BASES
B6: ▶ A. ÍNDICE Y ORDEN DE ENTREGA
B7: 1 | C7: Elaborar índice completo de todos los documentos a entregar | D7: Analista 1 | E7: CRÍTICO | F7: ✓ CUMPLE | H7: Control
B8: 2 | C8: Verificar que el orden coincide con lo exigido en bases | D8: Analista 2 | E8: ALTO | F8: ✓ CUMPLE | H8: Req. bases
B9: 3 | C9: Numerar y rotular volúmenes / sobres si las bases lo requieren | D9: Analista 2 | E9: ALTO | F9: ✓ CUMPLE | H9: Req. bases
B10: 4 | C10: Preparar versión digital (PDF) y física según requisitos de entrega | D10: Analista 1 | E10: CRÍTICO | F10: ✓ CUMPLE | H10: Req. bases
B11: 5 | C11: Revisar que tamaño de archivos digitales no excede límites del portal | D11: Analista 2 | E11: ALTO | F11: ✓ CUMPLE | H11: Req. bases
B13: ▶ B. FIRMAS Y AUTORIZACIONES
B14: 6 | C14: Identificar documentos que deben ir firmados por representante legal | D14: Jefe Propuesta | E14: CRÍTICO | F14: ✓ CUMPLE | H14: Fuera de bases
B15: 7 | C15: Verificar que firmas son en original (no fotocopias) si se exige | D15: Analista 1 | E15: CRÍTICO | F15: ✓ CUMPLE | H15: Fuera de bases
B16: 8 | C16: Verificar que poderes notariales están vigentes y autorizan al firmante | D16: Jefe Propuesta | E16: CRÍTICO | F16: ✓ CUMPLE | H16: Fuera de bases
B17: 9 | C17: Confirmar firma en todas las páginas si las bases lo exigen | D17: Analista 2 | E17: ALTO | F17: ⚠ PENDIENTE | H17: Req. bases
B19: ▶ C. FORMULARIOS OBLIGATORIOS
B20: 10 | C20: Formulario oferta técnica: completo, firmado y sin tachaduras | D20: Analista 1 | E20: CRÍTICO | F20: ⚠ PENDIENTE | H20: Fuera de bases
B21: 11 | C21: Formulario oferta económica: completo, firmado y sin errores | D21: Analista 1 | E21: CRÍTICO | F21: ⚠ PENDIENTE | H21: Fuera de bases
B22: 12 | C22: Declaración jurada de no conflicto de interés / inhabilidades | D22: Analista 2 | E22: CRÍTICO | F22: ⚠ PENDIENTE | H22: Fuera de bases
B23: 13 | C23: Anexo de equipo propuesto: completo con todos los profesionales | D23: Analista 1 | E23: CRÍTICO | F23: ⚠ PENDIENTE | H23: Fuera de bases
B24: 14 | C24: Ficha técnica del contrato (si es exigida) | D24: Analista 2 | E24: ALTO | F24: ⚠ PENDIENTE | H24: Req. bases
B25: 15 | C25: Comprobante / certificado de visita a terreno (si aplica) | D25: Analista 2 | E25: ALTO | F25: ⚠ PENDIENTE | H25: Req. bases
B26: 16 | C26: Documentos de la empresa: RUT, estatutos, escritura (si se exige) | D26: Analista 1 | E26: ALTO | F26: ⚠ PENDIENTE | H26: Req. bases
B28: ▶ D. VALIDACIÓN FINAL ANTES DE ENTREGA
B29: 17 | C29: Revisión cruzada final: índice vs documentos reales | D29: Jefe Propuesta | E29: CRÍTICO | F29: ⚠ PENDIENTE | H29: Control final
B30: 18 | C30: Contar páginas totales vs límite si hay restricción | D30: Analista 1 | E30: ALTO | F30: ⚠ PENDIENTE | H30: Req. bases
B31: 19 | C31: Verificar que archivos digitales abren correctamente (no corruptos) | D31: Analista 2 | E31: ALTO | F31: ⚠ PENDIENTE | H31: Control
B32: 20 | C32: Confirmar formato de archivos exigido (PDF, Word, firma digital) | D32: Analista 2 | E32: ALTO | F32: ⚠ PENDIENTE | H32: Req. bases
B33: 21 | C33: Buscar referencias a otros contratos por error de copiado (Ctrl+F) | D33: Analista 1 | E33: CRÍTICO | F33: ⚠ PENDIENTE | H33: Error grave
B34: 22 | C34: Revisar que no hay track changes / comentarios activos en documentos Word | D34: Analista 2 | E34: ALTO | F34: ⚠ PENDIENTE | H34: Presentación
B35: 23 | C35: Revisar metadatos de los archivos (no deben mostrar nombre de empresa rival) | D35: Analista 2 | E35: MEDIO | F35: ⚠ PENDIENTE | H35: Seguridad

Sheet CALIDAD
B2: CALIDAD
H3: =COUNTIF(F6:F500,"✓ CUMPLE") -> 0
B4: Completa el Estado con el dropdown. Agrega observaciones y evidencias en columna G.
B5: # | C5: ÍTEM / REQUISITO A VERIFICAR | D5: RESPONSABLE | E5: PRIORIDAD | F5: ESTADO | G5: OBSERVACIÓN / EVIDENCIA | H5: REF. BASES
B6: ▶ A. COHERENCIA INTERNA
B7: 1 | C7: Nombre del contrato es idéntico en todos los documentos | D7: Analista 2 | E7: CRÍTICO | F7: ⚠ PENDIENTE | H7: Consistencia
B8: 2 | C8: RUT y razón social de la empresa es idéntico en todos los documentos | D8: Analista 2 | E8: CRÍTICO | F8: ⚠ PENDIENTE | H8: Consistencia
B9: 3 | C9: Montos de la oferta económica son consistentes en todos los formularios | D9: Analista 1 | E9: CRÍTICO | F9: ⚠ PENDIENTE | H9: Consistencia
B10: 4 | C10: Profesionales nombrados en metodología = profesionales con CV adjunto | D10: Analista 1 | E10: ALTO | F10: ⚠ PENDIENTE | H10: Consistencia
B11: 5 | C11: Plazo propuesto en metodología coincide con el plazo ofertado | D11: Analista 2 | E11: ALTO | F11: ⚠ PENDIENTE | H11: Consistencia
B12: 6 | C12: Normativa citada en metodología es la correcta para el tipo de contrato | D12: Analista 1 | E12: ALTO | F12: ⚠ PENDIENTE | H12: Consistencia técnica
B14: ▶ B. CONTROL DE VERSIONES
B15: 7 | C15: Solo existe UNA versión final de cada documento (sin versiones previas) | D15: Analista 1 | E15: ALTO | F15: ⚠ PENDIENTE | H15: Control
B16: 8 | C16: Los archivos están nombrados correctamente según lo exigido en bases | D16: Analista 2 | E16: MEDIO | F16: ⚠ PENDIENTE | H16: Req. bases
B17: 9 | C17: No hay documentos con metadatos de otro contrato o empresa rival | D17: Analista 2 | E17: ALTO | F17: ⚠ PENDIENTE | H17: Seguridad
B18: 10 | C18: Propuesta no tiene track changes (seguimiento de cambios) activos | D18: Analista 1 | E18: ALTO | F18: ⚠ PENDIENTE | H18: Presentación
B19: 11 | C19: Los headers/footers de documentos muestran el nombre correcto del contrato | D19: Analista 2 | E19: MEDIO | F19: ⚠ PENDIENTE | H19: Consistencia
B21: ▶ C. PLAN INTERNO DE CALIDAD DE LA PROPUESTA
B22: 12 | C22: Se designó responsable de revisión final de calidad | D22: Jefe Propuesta | E22: CRÍTICO | F22: ⚠ PENDIENTE | H22: Control
B23: 13 | C23: Se definió plazo interno de cierre con margen de 24-48h antes de la apertura | D23: Jefe Propuesta | E23: CRÍTICO | F23: ⚠ PENDIENTE | H23: Riesgo plazo
B24: 14 | C24: Se designó quién imprime, empasta y entrega la propuesta física | D24: Analista 1 | E24: ALTO | F24: ⚠ PENDIENTE | H24: Logística
B25: 15 | C25: Respaldo digital de todos los documentos previo a la entrega | D25: Analista 1 | E25: CRÍTICO | F25: ⚠ PENDIENTE | H25: Trazabilidad
B26: 16 | C26: Se realizó revisión cruzada con al menos 2 personas del equipo | D26: Jefe Propuesta | E26: ALTO | F26: ⚠ PENDIENTE | H26: Control calidad

Sheet CIERRE
B2: CIERRE
H3: =COUNTIF(F6:F500,"✓ CUMPLE") -> 0
B4: Completa el Estado con el dropdown. Agrega observaciones y evidencias en columna G.
B5: # | C5: ÍTEM / REQUISITO A VERIFICAR | D5: RESPONSABLE | E5: PRIORIDAD | F5: ESTADO | G5: OBSERVACIÓN / EVIDENCIA | H5: REF. BASES
B6: ▶ A. 72 HORAS ANTES DE LA APERTURA
B7: 1 | C7: Versión final de metodología aprobada internamente | D7: Jefe Propuesta | E7: CRÍTICO | F7: ⚠ PENDIENTE | H7: D-3
B8: 2 | C8: Todos los CV revisados, firmados y ordenados | D8: Analista 1 | E8: CRÍTICO | F8: ⚠ PENDIENTE | H8: D-3
B9: 3 | C9: Todas las cartas compromiso recibidas y verificadas | D9: Analista 1 | E9: CRÍTICO | F9: ⚠ PENDIENTE | H9: D-3
B10: 4 | C10: Oferta económica cuadrada, revisada y aprobada | D10: Analista 1 | E10: CRÍTICO | F10: ⚠ PENDIENTE | H10: D-3
B11: 5 | C11: Garantía de seriedad solicitada al banco / aseguradora | D11: Jefe Propuesta | E11: CRÍTICO | F11: ⚠ PENDIENTE | H11: D-3
B12: 6 | C12: Todos los formularios completados y firmados | D12: Analista 2 | E12: CRÍTICO | F12: ⚠ PENDIENTE | H12: D-3
B14: ▶ B. 24 HORAS ANTES DE LA APERTURA
B15: 7 | C15: Todos los documentos impresos o en PDF final listos | D15: Analista 2 | E15: CRÍTICO | F15: ⚠ PENDIENTE | H15: D-1
B16: 8 | C16: Revisión cruzada final del índice vs contenido real | D16: Jefe Propuesta | E16: CRÍTICO | F16: ⚠ PENDIENTE | H16: D-1
B17: 9 | C17: Garantía física recibida y verificada (monto, plazo, beneficiario) | D17: Jefe Propuesta | E17: CRÍTICO | F17: ⚠ PENDIENTE | H17: D-1
B18: 10 | C18: Confirmación de lugar, hora y forma de entrega | D18: Analista 2 | E18: CRÍTICO | F18: ⚠ PENDIENTE | H18: D-1
B19: 11 | C19: Copia digital respaldada en nube / servidor interno | D19: Analista 1 | E19: CRÍTICO | F19: ⚠ PENDIENTE | H19: D-1
B20: 12 | C20: Se imprimió una copia de respaldo extra de cada documento clave | D20: Analista 1 | E20: ALTO | F20: ⚠ PENDIENTE | H20: D-1
B22: ▶ C. DÍA DE APERTURA
B23: 13 | C23: Llegar con al menos 30 minutos de anticipación al lugar de entrega | D23: Jefe Propuesta | E23: CRÍTICO | F23: ⚠ PENDIENTE | H23: D-Day
B24: 14 | C24: Llevar copia extra de cada documento crítico | D24: Analista 1 | E24: ALTO | F24: ⚠ PENDIENTE | H24: D-Day
B25: 15 | C25: Obtener comprobante de recepción / número de ingreso | D25: Analista 1 | E25: CRÍTICO | F25: ⚠ PENDIENTE | H25: D-Day
B26: 16 | C26: Asistir a apertura si es pública y registrar propuestas rivales y montos | D26: Jefe Propuesta | E26: ALTO | F26: ⚠ PENDIENTE | H26: Inteligencia
B27: 17 | C27: Registrar nombres de empresas y profesionales presentes | D27: Analista 2 | E27: MEDIO | F27: ⚠ PENDIENTE | H27: Inteligencia
B29: ▶ D. POST-APERTURA Y SEGUIMIENTO
B30: 18 | C30: Guardar acta de apertura publicada en portal MOP / MercadoPúblico | D30: Analista 2 | E30: ALTO | F30: ⚠ PENDIENTE | H30: Trazabilidad
B31: 19 | C31: Revisar puntajes publicados y analizar brecha con el ganador | D31: Jefe Propuesta | E31: ALTO | F31: ⚠ PENDIENTE | H31: Aprendizaje
B32: 20 | C32: Identificar si hay fundamento para observaciones o reclamo formal | D32: Jefe Propuesta | E32: MEDIO | F32: ⚠ PENDIENTE | H32: Estrategia
B33: 21 | C33: Documentar lecciones aprendidas para futuras propuestas | D33: Jefe Propuesta | E33: MEDIO | F33: ⚠ PENDIENTE | H33: Mejora continua
B34: 22 | C34: Archivar propuesta completa como memoria técnica de referencia | D34: Analista 1 | E34: MEDIO | F34: ⚠ PENDIENTE | H34: Trazabilidad

Sheet LISTAS
A1: ESTADO | B1: PRIORIDAD | C1: RESPONSABLE | D1: USO
A2: ✓ CUMPLE | B2: CRÍTICO | C2: Andres M | D2: Actualizar aquí las palabras sugeridas para mantener criterios homogéneos
A3: ⚠ PENDIENTE | B3: ALTO | C3: Rocío F.
A4: ✗ NO CUMPLE | B4: MEDIO | C4: Julio T.
A5: N/A | B5: BAJO | C5: Administración
C6: Legal
C7: Finanzas
