Workbook

Sheet RESUMEN
B2: INGRESOS
B3: ROCIO | C3: 1650000
B4: CRISTOBAL | C4: 1000000
B5: TOTAL | C5: =SUM(C3:C4) -> 2650000
B8: ITEM | C8: PRESUPUESTO | D8: GASTO REAL | E8: DIFERENCIA
B9: AHORRO | C9: 400000 | D9: 400000 | E9: =C9-D9 -> 0 | F9: ok
B10: GASTOS FIJOS | C10: 1000000 | D10: =GF!C19 -> 937109 | E10: =C10-D10 -> 62891
B11: SUPERMERCADO | C11: 450000 | D11: =supermercado!C22 -> 253231 | E11: =C11-D11 -> 196769 | G11: 196 | H11: super
B12: NIÑOS | C12: 110000 | D12: =GF!F19 -> 16990 | E12: =C12-D12 -> 93010
B13: SALUD | C13: 40000 | D13: =GF!O19 -> 0 | E13: =C13-D13 -> 40000
B14: PROVISIONES | C14: 261000 | D14: =GF!I19 -> 711530 | E14: =C14-D14 -> -450530
B15: PERSONALES | C15: 200000 | D15: =GF!L19 -> 44990 | E15: =C15-D15 -> 155010
B16: TOTAL | C16: =SUM(C9:C15) -> 2461000 | D16: =SUM(D9:D15) -> 2363850 | E16: =C16-D16 -> 97150
B17: DIFERENCIA | C17: =C5-C16 -> 189000
B18: TOTAL S+G | C18: =E16+C17 -> 286150
C19: =C18-E11 -> 89381

Sheet GF
B3: ITEM FIJOS | C3: GASTO | E3: ITEM NIÑOS | F3: GASTO | H3: ITEM PROVISIONES | I3: GASTOS | K3: PERSONALES | L3: MONTO | N3: SALUD | O3: GASTO
B4: ARRIENDO | C4: 368260 | E4: tete | F4: 12000 | H4: vacaciones | I4: 580000 | K4: ROCIO
B5: GASTO COMUN | C5: 56877 | E5: pijama hijo | F5: 4990 | H5: ropa colegio | I5: 131530 | K5: CRISTOBAL
B6: LUZ | C6: 42300 | K6: papa johns | L6: 19990
B7: AGUA | C7: 24873 | K7: hierba | L7: 25000
B8: GAS | C8: 45000
B9: PLAN CRISTOBAL | C9: 5318
B10: PLAN ROCIO | C10: 15550
B11: INTERNET | C11: 22071
B12: CHAT GPT | C12: 6560
B13: NETFLIX | C13: 9990
B14: SPOTIFY | C14: 8250
B15: BENCINA | C15: 75000
B16: MICRO | C16: 15000
B17: PASAJES MAMA | C17: 200000
B18: COMIDA Y ARENA G | C18: 42060
B19: TOTAL | C19: =SUM(C4:C18) -> 937109 | E19: TOTAL | F19: =SUM(F4:F18) -> 16990 | H19: TOTAL | I19: =SUM(I4:I18) -> 711530 | K19: TOTAL | L19: =SUM(L4:L18) -> 44990 | N19: TOTAL | O19: =SUM(O4:O18) -> 0
C22: =SUM(C8+C12+C14+E23+C17) -> 259810
D28: 57930
D29: 40240
D30: 6390 | H30: Vacaciones → 700.000
D31: 26970
D32: =SUM(D28:D31) -> 131530 | H32: Matrícula colegio → 900.000
H34: Útiles → 100.000
H36: Ropa colegio → 100.000
H38: Pascua → 30.000
H40: Cumpleaños varios → según calendario (Emma, Rocío, mamá, papá, suegro, Martín, abuelo)
H42: Navidad + Año Nuevo → 400.000

Sheet Hoja1
B2: ITEM FIJOS | C2: GASTO
B3: ARRIENDO | C3: 368260
B4: GASTO COMUN | C4: 56877
B5: LUZ | C5: 42300
B6: AGUA | C6: 24873
B7: GAS | C7: 45000
B8: PLAN CRISTOBAL | C8: 5318
B10: INTERNET | C10: 22071
B11: CHAT GPT | C11: 6560
B13: SPOTIFY | C13: 8250
B14: BENCINA | C14: 100000
B16: PASAJES MAMA | C16: 200000
B18: TOTAL | C18: =SUM(C3:C17) -> 879509

Sheet supermercado
B3: item | C3: valor
B4: ganga | C4: 56640
B5: feria | C5: 17400
B6: jumbo | C6: 5300
B7: huevos | C7: 11100
B8: ganga | C8: 22460
B9: lider | C9: 68280
B10: huevos | C10: 10600
B11: feria | C11: 14850
B12: feria | C12: 7500
B13: ganga | C13: 13000
B14: ganga | C14: 16421
B15: verluys | C15: 6520
B16: verluys | C16: 3160
B17: pedido
B22: total | C22: =SUM(C4:C21) -> 253231

Sheet Hoja2
B3: papa johns | C3: 19990
B4: vacaciones | C4: 580000
